__builtins__.pyi
_boot.pyi
_onewire.pyi
binascii.pyi
deflate.pyi
dht.pyi
ds18x20.pyi
errno.pyi
framebuf.pyi
gc.pyi
hashlib.pyi
heapq.pyi
machine.pyi
math.pyi
micropython.pyi
onewire.pyi
platform.pyi
random.pyi
samd.pyi
select.pyi
time.pyi
uarray.pyi
uasyncio.pyi
ubinascii.pyi
ubluetooth.pyi
ucollections.pyi
ucryptolib.pyi
uctypes.pyi
uerrno.pyi
uhashlib.pyi
uheapq.pyi
uio.pyi
ujson.pyi
umachine.pyi
uos.pyi
uplatform.pyi
urandom.pyi
ure.pyi
uselect.pyi
usocket.pyi
ussl.pyi
ustruct.pyi
usys.pyi
utime.pyi
uwebsocket.pyi
uzlib.pyi
vfs.pyi
micropython_samd_seeed_wio_terminal_stubs-1.27.0.post1.dist-info/LICENSE.md
micropython_samd_seeed_wio_terminal_stubs-1.27.0.post1.dist-info/METADATA
micropython_samd_seeed_wio_terminal_stubs-1.27.0.post1.dist-info/WHEEL
micropython_samd_seeed_wio_terminal_stubs-1.27.0.post1.dist-info/RECORD
